lange/__init__.py
lange/abs/__init__.py
lange/abs/progression.py
lange/ap.py
lange/gp.py
lange/tricks.py
lange/withbrackets.py
lange-1.230203.2.dist-info/LICENSE
lange-1.230203.2.dist-info/METADATA
lange-1.230203.2.dist-info/WHEEL
lange-1.230203.2.dist-info/RECORD
