Metadata-Version: 2.1
Name: lange
Version: 1.230203.2
Summary: Haskell-like intervals for Python
License: GPLv3
Author: davips
Author-email: dpsabc@gmail.com
Requires-Python: >=3.8,<4.0
Classifier: License :: Other/Proprietary License
Classifier: Programming Language :: Python :: 3
Classifier: Programming Language :: Python :: 3.8
Classifier: Programming Language :: Python :: 3.9
Classifier: Programming Language :: Python :: 3.10
Classifier: Programming Language :: Python :: 3.11
